{
  "slug": "como-calcular-salario-liquido",
  "meta_title": "Como Calcular Salário Líquido CLT 2026 | Tabelas INSS e IRRF Completas - CalcForgeTools",
  "meta_description": "Aprenda passo a passo como calcular seu salário líquido CLT com as tabelas progressivas de INSS e IRRF de 2026. Guia completo com exemplos práticos.",
  "hero": {
    "title": "Como Calcular Salário Líquido CLT",
    "subtitle": "O guia completo para entender cada centavo que sai do seu contracheque, dominar as tabelas de INSS e IRRF, e tomar o controle da sua vida financeira."
  },
  "related_tools": [
    {
      "id": "clt_salary",
      "href": "/pt/calculators/calculadora-salario-liquido-clt",
      "title": "Calculadora Salário Líquido CLT",
      "description": "Calcule seu salário líquido automaticamente com as tabelas 2026.",
      "category": "labor"
    }
  ],
  "content": [
    {
      "type": "quote",
      "text": "Não é o quanto você ganha que importa, é o quanto você leva para casa.",
      "author": "Robert Kiyosaki"
    },
    {
      "type": "paragraph",
      "text": "Você sabia que o brasileiro médio <strong>não sabe explicar</strong> por que o valor depositado na conta é menor do que o combinado no contrato? A realidade é brutal: entre o salário bruto prometido e o dinheiro que efetivamente chega na sua conta existem duas guilhotinas tributárias — o <strong>INSS</strong> e o <strong>IRRF</strong>. E ambos funcionam de forma progressiva, o que significa que quanto mais você ganha, mais aguda é a lâmina."
    },
    {
      "type": "paragraph",
      "text": "Entender como esses descontos funcionam não é apenas uma questão de curiosidade — é uma ferramenta de <strong>negociação salarial</strong>. Quando você sabe exatamente quanto sobra do bruto, consegue avaliar propostas de emprego com muito mais precisão e planejar seu orçamento pessoal de forma realista."
    },
    {
      "type": "heading",
      "text": "O Mapa dos Descontos: Tabela INSS 2026"
    },
    {
      "type": "paragraph",
      "text": "O INSS funciona por faixas progressivas. Você <strong>não paga 14% sobre tudo</strong> — cada trecho do seu salário é tributado por uma alíquota diferente. É como uma escada: cada degrau cobra uma taxa própria. Veja a tabela oficial vigente em 2026:"
    },
    {
      "type": "table",
      "headers": ["Faixa Salarial", "Alíquota INSS", "Contribuição Máxima na Faixa"],
      "rows": [
        ["Até R$ 1.621,00", "7,5%", "R$ 121,58"],
        ["De R$ 1.621,01 até R$ 2.902,84", "9%", "R$ 115,37"],
        ["De R$ 2.902,85 até R$ 4.354,27", "12%", "R$ 174,17"],
        ["De R$ 4.354,28 até R$ 8.475,55", "14%", "<strong>Teto: R$ 988,09</strong>"]
      ]
    },
    {
      "type": "paragraph",
      "text": "Se você ganha R$ 4.000, o cálculo real do INSS é: R$ 121,58 (1ª faixa) + R$ 115,37 (2ª faixa) + R$ 131,66 (3ª faixa parcial) = <strong>R$ 368,61</strong>. Muita gente pensa que paga 12% sobre os R$ 4.000 inteiros (que seria R$ 480), mas na realidade paga bem menos graças ao sistema progressivo."
    },
    {
      "type": "heading",
      "text": "A Segunda Guilhotina: Tabela IRRF 2026"
    },
    {
      "type": "paragraph",
      "text": "Depois de descontar o INSS do seu bruto, o que sobra entra na base de cálculo do Imposto de Renda Retido na Fonte. Cada dependente registrado <strong>reduz R$ 189,59</strong> dessa base. Veja as faixas de 2026:"
    },
    {
      "type": "table",
      "headers": ["Base de Cálculo (após INSS)", "Alíquota IRRF", "Dedução"],
      "rows": [
        ["Até R$ 2.428,80", "Isento", "—"],
        ["De R$ 2.428,81 até R$ 2.826,65", "7,5%", "R$ 182,16"],
        ["De R$ 2.826,66 até R$ 3.751,05", "15%", "R$ 394,16"],
        ["De R$ 3.751,06 até R$ 4.664,68", "22,5%", "R$ 692,78"],
        ["Acima de R$ 4.664,68", "27,5%", "R$ 908,73"]
      ]
    },
    {
      "type": "heading",
      "text": "A Novidade de 2026: Isenção até R$ 5.000"
    },
    {
      "type": "paragraph",
      "text": "A Lei nº 15.270/2025 trouxe uma mudança histórica: quem ganha até <strong>R$ 5.000 brutos está totalmente isento de IRRF</strong> a partir de janeiro de 2026. Para rendimentos entre R$ 5.000,01 e R$ 7.350,00, aplica-se um mecanismo de redução decrescente (quanto mais próximo de R$ 5.000, maior o desconto). Acima de R$ 7.350, aplica-se a tabela progressiva tradicional sem redução."
    },
    {
      "type": "paragraph",
      "text": "A coluna 'Dedução' é essencial. Ela corrige o fato de que a alíquota só se aplica à parcela que excede o limite inferior da faixa. Sem a dedução, o imposto seria cobrado sobre a base inteira — o que dobraria o desconto."
    },
    {
      "type": "heading",
      "text": "A Fórmula Completa Passo a Passo"
    },
    {
      "type": "formula",
      "expression": "Salário Líquido = Salário Bruto − INSS (progressivo) − IRRF (progressivo) − Outras Deduções"
    },
    {
      "type": "paragraph",
      "text": "A ordem de cálculo é crítica: <strong>primeiro</strong> desconta-se o INSS do bruto, <strong>depois</strong> subtrai-se a dedução por dependentes, <strong>então</strong> calcula-se o IRRF sobre o que sobrou (base de cálculo). Errar a ordem muda completamente o resultado."
    },
    {
      "type": "heading",
      "text": "Exemplo Prático Completo"
    },
    {
      "type": "paragraph",
      "text": "Maria ganha R$ 5.000 brutos e tem 1 dependente. Veja o passo a passo:"
    },
    {
      "type": "table",
      "headers": ["Etapa", "Cálculo", "Resultado"],
      "rows": [
        ["1. INSS Progressivo", "R$ 121,58 + R$ 115,37 + R$ 174,17 + R$ 90,40", "<strong>R$ 501,52</strong>"],
        ["2. Base IRRF", "R$ 5.000 - R$ 501,52 - R$ 189,59 (dependente)", "R$ 4.308,89"],
        ["3. IRRF Tradicional", "R$ 4.308,89 × 22,5% - R$ 692,78", "R$ 276,72"],
        ["4. Redução Lei 15.270", "R$ 978,62 - (0,133145 × R$ 5.000) = R$ 312,89", "Isenta (≤ R$ 5.000)"],
        ["5. IRRF Final", "R$ 0,00 (isenção total)", "<strong>R$ 0,00</strong>"],
        ["6. Salário Líquido", "R$ 5.000 - R$ 501,52 - R$ 0", "<strong>R$ 4.498,48</strong>"]
      ]
    },
    {
      "type": "heading",
      "text": "O FGTS: A Reserva Invisível"
    },
    {
      "type": "paragraph",
      "text": "Além dos descontos, existe o <strong>FGTS (8% do bruto)</strong>, que é depositado pelo empregador em uma conta vinculada na Caixa Econômica Federal. Ele <strong>não é descontado</strong> do seu salário — é um custo adicional da empresa. No exemplo da Maria, a empresa deposita R$ 400,00 de FGTS por mês, que ela só pode sacar em situações específicas como demissão sem justa causa, compra de imóvel, aposentadoria ou saque-aniversário."
    },
    {
      "type": "heading",
      "text": "Outras Deduções Comuns"
    },
    {
      "type": "paragraph",
      "text": "Além de INSS e IRRF, seu contracheque pode ter outros descontos legais: <strong>vale-transporte</strong> (até 6% do salário), <strong>vale-refeição</strong> (até 20% do valor concedido), <strong>plano de saúde/odontológico</strong> (coparticipação), <strong>pensão alimentícia judicial</strong>, <strong>contribuição sindical</strong> (apenas se autorizada) e <strong>empréstimo consignado</strong> (limitado a 35% do salário líquido). Todos esses descontos devem estar discriminados no contracheque."
    },
    {
      "type": "heading",
      "text": "Dicas para Maximizar Seu Líquido"
    },
    {
      "type": "paragraph",
      "text": "Existem formas legais de aumentar seu salário líquido sem mudar de emprego: (1) <strong>registrar todos os dependentes</strong> no RH — cada um reduz R$ 189,59 da base do IRRF; (2) <strong>declarar despesas médicas e educacionais</strong> na declaração anual para restituição; (3) <strong>contribuir para previdência privada PGBL</strong> — até 12% da renda bruta anual é dedutível do IR; (4) <strong>negociar benefícios não-tributados</strong> como vale-alimentação, plano de saúde e auxílio home-office, que não incidem INSS/IRRF."
    }
  ]
}
